<?xml version="1.0" encoding="utf-8" ?>
<Defs>
  
  <SoundDef>
    <defName>ROMV_LevelUp</defName>  
    <eventNames />  
    <maxSimultaneous>1</maxSimultaneous>  
    <subSounds>
      <li>
        <onCamera>True</onCamera>      
        <grains>
          <li Class="AudioGrain_Clip">
            <clipPath>UI/VampLevelUp</clipPath>
          </li>
        </grains>      
        <volumeRange>
          <min>50</min>        
          <max>50</max>
        </volumeRange>
      </li>
    </subSounds>
  </SoundDef>

  <SoundDef>
    <defName>ROMV_GoodSound</defName>  
    <eventNames />  
    <maxSimultaneous>1</maxSimultaneous>  
    <subSounds>
      <li>
        <onCamera>True</onCamera>      
        <grains>
          <li Class="AudioGrain_Clip">
            <clipPath>UI/VampGood</clipPath>
          </li>
        </grains>      
        <volumeRange>
          <min>50</min>        
          <max>50</max>
        </volumeRange>
      </li>
    </subSounds>
  </SoundDef>

  <SoundDef>
    <defName>ROMV_BadSound</defName>  
    <eventNames />  
    <maxSimultaneous>1</maxSimultaneous>  
    <subSounds>
      <li>
        <onCamera>True</onCamera>      
        <grains>
          <li Class="AudioGrain_Clip">
            <clipPath>UI/VampBad</clipPath>
          </li>
        </grains>      
        <volumeRange>
          <min>50</min>        
          <max>50</max>
        </volumeRange>
      </li>
    </subSounds>
  </SoundDef>

  <SoundDef>
    <defName>ROMV_FrenzySound</defName>  
    <eventNames />  
    <maxSimultaneous>1</maxSimultaneous>  
    <subSounds>
      <li>
        <onCamera>True</onCamera>      
        <grains>
          <li Class="AudioGrain_Clip">
            <clipPath>UI/VampFrenzy</clipPath>
          </li>
        </grains>      
        <volumeRange>
          <min>50</min>        
          <max>50</max>
        </volumeRange>
      </li>
    </subSounds>
  </SoundDef>

</Defs>